cwhite_simple_proxy-0.2.0.dist-info/licenses/LICENSE
simpleproxy/__init__.py
simpleproxy/__main__.py
simpleproxy/simple_proxy_init.py
simpleproxy/test_remote_server.py
simpleproxy/src/__init__.py
simpleproxy/src/cli.py
simpleproxy/src/cloud_provider.py
simpleproxy/src/providers/__init__.py
simpleproxy/src/providers/aws_fargate.py
simpleproxy/src/providers/kubernetes_base.py
simpleproxy/src/providers/vultr_vke.py
cwhite_simple_proxy-0.2.0.dist-info/METADATA
cwhite_simple_proxy-0.2.0.dist-info/WHEEL
cwhite_simple_proxy-0.2.0.dist-info/entry_points.txt
cwhite_simple_proxy-0.2.0.dist-info/top_level.txt
cwhite_simple_proxy-0.2.0.dist-info/RECORD
