Metadata-Version: 2.4
Name: cwhite-simple-proxy
Version: 0.2.0
Summary: Deploy proxy servers to cloud providers with ease
Author: Simple Proxy Contributors
License: MIT
Project-URL: Homepage, https://github.com/calderwhite/simple-proxy
Project-URL: Repository, https://github.com/calderwhite/simple-proxy
Project-URL: Issues, https://github.com/calderwhite/simple-proxy/issues
Keywords: proxy,aws,fargate,vultr,vke,kubernetes,cloud,deployment
Classifier: Development Status :: 4 - Beta
Classifier: Intended Audience :: Developers
Classifier: License :: OSI Approved :: MIT License
Classifier: Programming Language :: Python :: 3
Classifier: Programming Language :: Python :: 3.8
Classifier: Programming Language :: Python :: 3.9
Classifier: Programming Language :: Python :: 3.10
Classifier: Programming Language :: Python :: 3.11
Classifier: Programming Language :: Python :: 3.12
Classifier: Topic :: Internet :: Proxy Servers
Classifier: Topic :: System :: Networking
Requires-Python: >=3.8
License-File: LICENSE
Requires-Dist: boto3>=1.40.0
Requires-Dist: requests>=2.32.0
Requires-Dist: kubernetes>=30.0.0
Requires-Dist: pyyaml>=6.0
Provides-Extra: dev
Requires-Dist: pytest>=8.4.0; extra == "dev"
Requires-Dist: pytest-asyncio>=1.0.0; extra == "dev"
Requires-Dist: aiohttp>=3.13.0; extra == "dev"
Dynamic: license-file
